importspy/__init__.py
importspy/cli.py
importspy/config.py
importspy/constants.py
importspy/log_manager.py
importspy/models.py
importspy/persistences.py
importspy/s.py
importspy/utilities/__init__.py
importspy/utilities/module_util.py
importspy/utilities/python_util.py
importspy/utilities/runtime_util.py
importspy/utilities/system_util.py
importspy/validators.py
importspy/violation_systems.py
importspy-0.4.6.dist-info/LICENSE
importspy-0.4.6.dist-info/METADATA
importspy-0.4.6.dist-info/WHEEL
importspy-0.4.6.dist-info/entry_points.txt
importspy-0.4.6.dist-info/RECORD
