Metadata-Version: 2.3
Name: importspy
Version: 0.4.6
Summary: ImportSpy ensures structural integrity, runtime compliance, and security for external modules, preventing inconsistencies and enforcing controlled execution.
License: MIT
Author: Luca Atella
Author-email: atellaluca@outlook.it
Requires-Python: >=3.10,<4.0
Classifier: License :: OSI Approved :: MIT License
Classifier: Programming Language :: Python :: 3
Classifier: Programming Language :: Python :: 3.10
Classifier: Programming Language :: Python :: 3.11
Classifier: Programming Language :: Python :: 3.12
Classifier: Programming Language :: Python :: 3.13
Requires-Dist: pydantic (>=2.9.2,<3.0.0)
Requires-Dist: pymdown-extensions (>=10.16.1,<11.0.0)
Requires-Dist: ruamel-yaml (>=0.18.10,<0.19.0)
Requires-Dist: typer (>=0.15.2,<0.16.0)
Project-URL: Documentation, https://importspy.readthedocs.io
Project-URL: Repository, https://github.com/atellaluca/importspy
